keap_core_v2_client/__init__.py
keap_core_v2_client/api_client.py
keap_core_v2_client/api_response.py
keap_core_v2_client/configuration.py
keap_core_v2_client/exceptions.py
keap_core_v2_client/py.typed
keap_core_v2_client/rest.py
keap_core_v2_client/api/__init__.py
keap_core_v2_client/api/affiliate_api.py
keap_core_v2_client/api/automation_api.py
keap_core_v2_client/api/automation_category_api.py
keap_core_v2_client/api/business_profile_api.py
keap_core_v2_client/api/campaign_api.py
keap_core_v2_client/api/category_discounts_api.py
keap_core_v2_client/api/company_api.py
keap_core_v2_client/api/contact_api.py
keap_core_v2_client/api/email_address_api.py
keap_core_v2_client/api/email_api.py
keap_core_v2_client/api/files_api.py
keap_core_v2_client/api/free_trial_discounts_api.py
keap_core_v2_client/api/lead_score_api.py
keap_core_v2_client/api/lead_source_categories_api.py
keap_core_v2_client/api/lead_source_expenses_api.py
keap_core_v2_client/api/lead_source_recurring_expenses_api.py
keap_core_v2_client/api/lead_sources_api.py
keap_core_v2_client/api/locale_api.py
keap_core_v2_client/api/merchants_api.py
keap_core_v2_client/api/note_api.py
keap_core_v2_client/api/opportunity_api.py
keap_core_v2_client/api/order_total_discounts_api.py
keap_core_v2_client/api/orders_api.py
keap_core_v2_client/api/payment_method_configs_api.py
keap_core_v2_client/api/payment_methods_api.py
keap_core_v2_client/api/product_categories_api.py
keap_core_v2_client/api/product_discounts_api.py
keap_core_v2_client/api/product_interest_bundles_api.py
keap_core_v2_client/api/products_api.py
keap_core_v2_client/api/referral_api.py
keap_core_v2_client/api/reporting_api.py
keap_core_v2_client/api/sales_api.py
keap_core_v2_client/api/settings_api.py
keap_core_v2_client/api/shipping_api.py
keap_core_v2_client/api/shipping_discounts_api.py
keap_core_v2_client/api/subscription_plans_api.py
keap_core_v2_client/api/subscriptions_api.py
keap_core_v2_client/api/tags_api.py
keap_core_v2_sdk-1.0.40.dist-info/METADATA
keap_core_v2_sdk-1.0.40.dist-info/WHEEL
keap_core_v2_sdk-1.0.40.dist-info/top_level.txt
keap_core_v2_sdk-1.0.40.dist-info/RECORD
