Metadata-Version: 2.4
Name: keap-core-v2-sdk
Version: 1.0.40
Summary: Keap REST API
Home-page: https://github.com/infusionsoft/keap-sdk.git
Author: Keap
Author-email: api@keap.com
License: Apache 2.0
Keywords: OpenAPI,OpenAPI-Generator,Keap REST API
Requires-Dist: urllib3<3.0.0,>=2.1.0
Requires-Dist: python-dateutil>=2.8.2
Requires-Dist: pydantic>=2
Requires-Dist: typing-extensions>=4.7.1
Dynamic: author
Dynamic: author-email
Dynamic: description
Dynamic: description-content-type
Dynamic: home-page
Dynamic: keywords
Dynamic: license
Dynamic: requires-dist
Dynamic: summary
